pinecone_text/__init__.py
pinecone_text/dense/__init__.py
pinecone_text/dense/base_dense_ecoder.py
pinecone_text/dense/cohere_encoder.py
pinecone_text/dense/jina_encoder.py
pinecone_text/dense/openai_encoder.py
pinecone_text/dense/sentence_transformer_encoder.py
pinecone_text/hybrid/__init__.py
pinecone_text/hybrid/hybrid_convex.py
pinecone_text/sparse/__init__.py
pinecone_text/sparse/base_sparse_encoder.py
pinecone_text/sparse/bm25_encoder.py
pinecone_text/sparse/bm25_tokenizer.py
pinecone_text/sparse/splade_encoder.py
pinecone_text-0.8.0.dist-info/WHEEL
pinecone_text-0.8.0.dist-info/LICENSE.txt
pinecone_text-0.8.0.dist-info/METADATA
pinecone_text-0.8.0.dist-info/RECORD
