Metadata-Version: 2.1
Name: pinecone-text
Version: 0.8.0
Summary: Text utilities library by Pinecone.io
Author: Pinecone.io
Requires-Python: >=3.8,<4.0
Classifier: Programming Language :: Python :: 3
Classifier: Programming Language :: Python :: 3.8
Classifier: Programming Language :: Python :: 3.9
Classifier: Programming Language :: Python :: 3.10
Classifier: Programming Language :: Python :: 3.11
Provides-Extra: cohere
Provides-Extra: dense
Provides-Extra: openai
Provides-Extra: splade
Requires-Dist: cohere (>=4.37,<5.0) ; extra == "cohere"
Requires-Dist: mmh3 (>=3.1.0,<4.0.0)
Requires-Dist: nltk (>=3.6.5,<4.0.0)
Requires-Dist: numpy (>=1.21.5,<2.0) ; python_version < "3.12"
Requires-Dist: numpy (>=1.26,<2.0) ; python_version >= "3.12"
Requires-Dist: openai (>=1.2.3,<2.0.0) ; extra == "dense" or extra == "openai"
Requires-Dist: python-dotenv (>=1.0.1,<2.0.0)
Requires-Dist: requests (>=2.25.0,<3.0.0)
Requires-Dist: sentence-transformers (>=2.0.0) ; extra == "splade" or extra == "dense"
Requires-Dist: torch (>=1.13.1) ; extra == "splade" or extra == "dense"
Requires-Dist: transformers (>=4.26.1) ; extra == "splade" or extra == "dense"
Requires-Dist: types-requests (>=2.25.0,<3.0.0)
Requires-Dist: wget (>=3.2,<4.0)
